dlai_tools/__init__.py
dlai_tools/custom_grader.py
dlai_tools/deploy_assignment.py
dlai_tools/learner_generator.py
dlai_tools/test_custom_grader.py
dlai_tools/test_testing_utils.py
dlai_tools/test_toc.py
dlai_tools/test_utils.py
dlai_tools/testing_utils.py
dlai_tools/toc.py
tests/__init__.py
tests/test_add_toc__.py
tests/test_test_utils.py
dlai_tools-0.6.1.dist-info/METADATA
dlai_tools-0.6.1.dist-info/WHEEL
dlai_tools-0.6.1.dist-info/top_level.txt
dlai_tools-0.6.1.dist-info/RECORD
