Metadata-Version: 2.1
Name: dlai_tools
Version: 0.6.1
Summary: Deployment script for notebooks
Home-page: https://github.com/https-deeplearning-ai/dlai_tools
Download-URL: https://github.com/https-deeplearning-ai/dlai_tools/releases/tag/0.6.1
Author: Andrés Castillo
Author-email: andcastillo@gmail.com
Classifier: Programming Language :: Python :: 3
Classifier: License :: OSI Approved :: MIT License
Classifier: Operating System :: OS Independent
Requires-Python: >=3.6
